{
  "Suppliers": "/suppliers",
  "SignIn": "/",
  "Register": "/register",
  "Verification": "/verification",
  "ForgotPassword": "/forgot-password",
  "Logout": "/logout",
  "ResetPassword": "/reset-password",
  "Settings": "/settings",
  "Terms": "/terms",
  "Policy": "/policy",
  "Dashboard": "/",
  "Inventory": "/inventory",
  "NewProduct": "/new-product",
  "Orders": "/orders",
  "Archived": "/orders/archived",
  "Returns": "/orders/returns",
  "Cancellations": "/orders/cancellations",
  "Onboarding": "/onboarding",
  "BankingInfo": "/banking-info",
  "ShippingAndReturn": "/shipping-return",
  "AboutYou": "/about-you",
  "SellerAgreement": "/seller-agreement",
  "YourBusiness": "/your-business",
  "YourCatalog": "/your-catalog",
  "BusinessPresence": "/business-presence",
  "Help": "/help",
  "ShippingPolicy": "/shipping-policy"
}
